changing_dot/__init__.py
changing_dot/apply_graph_changes.py
changing_dot/changing_graph/changing_graph.py
changing_dot/checks/check_if_duplicate_solution.py
changing_dot/checks/check_solution_syntax_correctness.py
changing_dot/checks/check_solution_validity.py
changing_dot/checks/merge_cycles.py
changing_dot/commit/commit_edits.py
changing_dot/commit/conflict_handler.py
changing_dot/commit/reset_repo.py
changing_dot/commit_graph.py
changing_dot/config/__init__.py
changing_dot/config/constants.py
changing_dot/config/environment.py
changing_dot/config/py.typed
changing_dot/create_graph.py
changing_dot/custom_types.py
changing_dot/dependency_graph/dependency_graph.py
changing_dot/dependency_graph/language_matchers.py
changing_dot/dependency_graph/node_type_to_terminal.py
changing_dot/dependency_graph/types.py
changing_dot/error_manager/error_manager.py
changing_dot/error_manager/mypy_error_manager.py
changing_dot/error_manager/roslyn_error_manager.py
changing_dot/generated_grpc/feedback_server_pb2.py
changing_dot/generated_grpc/feedback_server_pb2_grpc.py
changing_dot/generated_grpc_types/feedback_server_pb2.pyi
changing_dot/handle_node.py
changing_dot/instruction_interpreter/block_instruction_interpreter.py
changing_dot/instruction_interpreter/block_prompts.py
changing_dot/instruction_interpreter/hard_coded_instruction_interpreter.py
changing_dot/instruction_interpreter/instruction_interpreter.py
changing_dot/instruction_manager/block_instruction_manager/block_instruction_manager.py
changing_dot/instruction_manager/block_instruction_manager/prompt.py
changing_dot/instruction_manager/hard_coded_instruction_manager.py
changing_dot/instruction_manager/instruction_manager.py
changing_dot/modifyle/modifyle.py
changing_dot/optimize_graph.py
changing_dot/py.typed
changing_dot/resolve_graph.py
changing_dot/resume_graph.py
changing_dot/utils/__init__.py
changing_dot/utils/file_utils.py
changing_dot/utils/get_algorithm_language.py
changing_dot/utils/llm_model_utils.py
changing_dot-0.0.1a9.dist-info/METADATA
changing_dot-0.0.1a9.dist-info/WHEEL
changing_dot-0.0.1a9.dist-info/entry_points.txt
changing_dot-0.0.1a9.dist-info/RECORD
