Metadata-Version: 2.1
Name: changing-dot
Version: 0.0.1a9
Summary: ChangingDot Repo
Author: Matthieu Rossignon
Author-email: matthieu.rossignon@hotmail.fr
Requires-Python: ==3.11.4
Classifier: Programming Language :: Python :: 3
Requires-Dist: cdot-tree-sitter-python (>=0.21.0,<0.22.0)
Requires-Dist: click (>=8.1.7,<9.0.0)
Requires-Dist: gitpython (>=3.1.42,<4.0.0)
Requires-Dist: grpcio (>=1.60.0,<2.0.0)
Requires-Dist: langchain (>=0.1.0,<0.2.0)
Requires-Dist: langchain-mistralai (>=0.0.2.post1,<0.0.3)
Requires-Dist: langchain-openai (>=0.0.2.post1,<0.0.3)
Requires-Dist: loguru (>=0.7.0,<0.8.0)
Requires-Dist: mypy (>=1.9.0,<2.0.0)
Requires-Dist: nbformat (>=5.9.2,<6.0.0)
Requires-Dist: networkx (>=3.2.1,<4.0.0)
Requires-Dist: python-dotenv (>=1.0.0,<2.0.0)
Requires-Dist: pyyaml (>=6.0.1,<7.0.0)
Requires-Dist: tree-sitter (>=0.22.3,<0.23.0)
Requires-Dist: tree-sitter-c-sharp (>=0.21.3,<0.22.0)
Requires-Dist: tree-sitter-requirements (>=0.4.0,<0.5.0)
Requires-Dist: tree-sitter-xml (>=0.6.4,<0.7.0)
Requires-Dist: visdcc (>=0.0.50,<0.0.51)
Requires-Dist: vizro (>=0.1.11,<0.2.0)
Requires-Dist: wandb (>=0.16.6,<0.17.0)
